{
  "as_of": "2026-02-21",
  "goal": {
    "period_start": "2026-01-01",
    "target_date": "2026-12-22",
    "target_total": 30000,
    "current_total_2026": 4392,
    "expected_total_by_today": 4382.02,
    "ahead_behind": 9.98,
    "required_per_day_remaining": 83.96,
    "projected_total_by_target_30d_pace": 34082.67,
    "on_pace_today": true
  },
  "consistency": {
    "avg_7d": 36.71,
    "avg_30d": 97.67,
    "active_days_30d": 28
  },
  "risk": {
    "last_7d_total": 257,
    "prior_7d_total": 845,
    "weekly_jump_pct": -69.59,
    "high_ramp_risk": false
  },
  "totals": {
    "lifetime_all_years": 4452
  },
  "interpretation": {
    "pace": {
      "status": "On pace",
      "advice": "Stay steady. Keep daily output near your 30-day average."
    },
    "consistency": {
      "status": "Cooling",
      "advice": "Recent week is below baseline. Add one extra session block this week."
    },
    "risk": {
      "status": "Detraining risk",
      "advice": "Recent drop is steep. Rebuild with small daily targets this week."
    }
  },
  "pro_dev": [
    {
      "name": "One Lead Metric",
      "why": "Top performers anchor behavior to a single pace number each day.",
      "action": "Hit or exceed required pace: 83.96 reps/day."
    },
    {
      "name": "Consistency Before Intensity",
      "why": "Sustained frequency compounds faster than occasional spikes.",
      "action": "Target >= 24 active days per 30 days (currently 28)."
    },
    {
      "name": "Progressive Overload With Guardrails",
      "why": "Improvement comes from controlled increases, not random jumps.",
      "action": "Keep week-over-week volume change between 0% and +20% when possible."
    }
  ],
  "coach_note": "This week: rebuild consistency. Add one extra training day and match your 30-day average."
}
